{
  "usuarios": [
		{
      "nombre": "Adur",
      "apellidos": "Administrador A",
			"perfil": "Administrador"
    },
		{
      "nombre": "Jorge",
      "apellidos": "Administrador J",
			"perfil": "Administrador"
    },
    {
      "nombre": "Sergio",
      "apellidos": "Administrador S",
			"perfil": "Administrador"
    },
		{
      "nombre": "Protectora Estella",
      "apellidos": "",
			"perfil": "Entidad"
    },
		{
      "nombre": "Pablo",
      "apellidos": "Adoptante Gatos",
			"perfil": "Adoptante"
    }
  ],
	"mascotas": [
		{
			"tipo": "Gato",
			"nombre": "Gatito",
			"entidad": "Protectora Estella",
			"edad": 3,
			"prioridad": 3
		},
		{
			"tipo": "Perro",
			"nombre": "Perrico",
			"entidad": "Protectora Estella",
			"edad": 2,
			"prioridad": 2
		}
	]
}
